README.rst
setup.py
./__init__.py
./base.py
./exceptions.py
./loaders.py
./mappers.py
./util.py
./version.py
gis/__init__.py
gis/mixins.py
parsers/__init__.py
parsers/base.py
parsers/readers.py
parsers/text.py
parsers/xls.py
wq/__init__.py
wq.io.egg-info/PKG-INFO
wq.io.egg-info/SOURCES.txt
wq.io.egg-info/dependency_links.txt
wq.io.egg-info/namespace_packages.txt
wq.io.egg-info/requires.txt
wq.io.egg-info/top_level.txt