Metadata-Version: 1.1
Name: wq.io
Version: 0.7.1
Summary: Consistent iterable API for reading and writing to external datasets
Home-page: http://wq.io/wq.io
Author: S. Andrew Sheppard
Author-email: andrew@wq.io
License: MIT
Platform: UNKNOWN
Classifier: Development Status :: 5 - Production/Stable
Classifier: License :: OSI Approved :: MIT License
Classifier: Natural Language :: English
Classifier: Programming Language :: Python :: 2
Classifier: Programming Language :: Python :: 2.7
Classifier: Programming Language :: Python :: 3
Classifier: Programming Language :: Python :: 3.4
Classifier: Intended Audience :: Science/Research
Classifier: Intended Audience :: Developers
Classifier: Topic :: Software Development :: Libraries :: Application Frameworks
Classifier: Topic :: Text Processing :: Markup :: XML
Classifier: Topic :: Scientific/Engineering :: GIS
Classifier: Topic :: Utilities
